eve_elastic/__init__.py
eve_elastic/elastic.py
eve_elastic/validation.py
Eve_Elastic-7.4.3.dist-info/AUTHORS.md
Eve_Elastic-7.4.3.dist-info/LICENSE
Eve_Elastic-7.4.3.dist-info/METADATA
Eve_Elastic-7.4.3.dist-info/WHEEL
Eve_Elastic-7.4.3.dist-info/top_level.txt
Eve_Elastic-7.4.3.dist-info/RECORD
