Metadata-Version: 2.1
Name: Eve-Elastic
Version: 7.4.3
Summary: Elasticsearch data layer for eve rest framework
Author: Petr Jasek, Mark Pittaway
License: GNU GENERAL PUBLIC LICENSE
Project-URL: Repository, https://github.com/superdesk/eve-elastic
Classifier: Development Status :: 5 - Production/Stable
Classifier: Environment :: Web Environment
Classifier: Intended Audience :: Developers
Classifier: License :: OSI Approved :: GNU General Public License v3 (GPLv3)
Classifier: Operating System :: OS Independent
Classifier: Programming Language :: Python
Classifier: Programming Language :: Python :: 3
Classifier: Topic :: Internet :: WWW/HTTP :: Dynamic Content
Requires-Python: >=3.9
License-File: LICENSE
License-File: AUTHORS.md
Requires-Dist: arrow>=0.4.2
Requires-Dist: ciso8601<3,>=1.0.2
Requires-Dist: pytz>=2015.4
Requires-Dist: elasticsearch<8.0,>=7.0
